_genpdf2/__init__.py
_genpdf2/main.py
_genpdf2/deposit/__init__.py
_genpdf2/deposit/pdfgen.py
_genpdf2/deposit/utilitaires.py
genpdf-0.2.dist-info/METADATA
genpdf-0.2.dist-info/WHEEL
genpdf-0.2.dist-info/top_level.txt
genpdf-0.2.dist-info/RECORD
