Metadata-Version: 2.1
Name: genpdf
Version: 0.2
